Metadata-Version: 2.4
Name: coq-tools
Version: 0.0.42
Summary: Some scripts to help manipulate Coq developments and minimize error-producing Coq code
Author-email: Jason Gross <jgross@mit.edu>
Project-URL: Homepage, https://github.com/JasonGross/coq-tools
Project-URL: Bug Tracker, https://github.com/JasonGross/coq-tools/issues
Classifier: Programming Language :: Python :: 3
Classifier: License :: OSI Approved :: MIT License
Classifier: Operating System :: OS Independent
Requires-Python: >=3.6
License-File: LICENSE
Requires-Dist: subprocess4>=0.1.1
Provides-Extra: test
Requires-Dist: resource; extra == "test"
Requires-Dist: pytest; extra == "test"
Requires-Dist: pytest-doctestplus; extra == "test"
Provides-Extra: all
Requires-Dist: resource; extra == "all"
Requires-Dist: coq-tools[test]; extra == "all"
Dynamic: license-file
